{"name":"Angola","iso":"AGO","states":[{"name":"Bengo Province","code":"BGO","cities":[{"name":"Caxito"}]},{"name":"Benguela Province","code":"BGU","cities":[{"name":"Benguela"},{"name":"Catumbela"},{"name":"Lobito"}]},{"name":"Bié Province","code":"BIE","cities":[{"name":"Camacupa"},{"name":"Catabola"},{"name":"Chissamba"},{"name":"Cuito"}]},{"name":"Cabinda Province","code":"CAB","cities":[{"name":"Cabinda"}]},{"name":"Cuando Cubango Province","code":"CCU","cities":[{"name":"Menongue"}]},{"name":"Cuanza Norte Province","code":"CNO","cities":[{"name":"Camabatela"},{"name":"N’dalatando"}]},{"name":"Cuanza Sul","code":"CUS","cities":[{"name":"Quibala"},{"name":"Sumbe"},{"name":"Uacu Cungo"}]},{"name":"Cunene Province","code":"CNN","cities":[{"name":"Ondjiva"}]},{"name":"Huambo Province","code":"HUA","cities":[{"name":"Caála"},{"name":"Chela"},{"name":"Huambo"},{"name":"Longonjo"}]},{"name":"Huíla Province","code":"HUI","cities":[{"name":"Caconda"},{"name":"Caluquembe"},{"name":"Chibia"},{"name":"Chicomba"},{"name":"Chipindo"},{"name":"Cuvango"},{"name":"Gambos"},{"name":"Humpata"},{"name":"Jamba"},{"name":"Lubango"},{"name":"Matala"},{"name":"Quilengues"},{"name":"Quipungo"}]},{"name":"Luanda Province","code":"LUA","cities":[{"name":"Belas"},{"name":"Icolo e Bengo"},{"name":"Luanda"}]},{"name":"Lunda Norte Province","code":"LNO","cities":[{"name":"Lucapa"}]},{"name":"Lunda Sul Province","code":"LSU","cities":[{"name":"Cazaji"},{"name":"Saurimo"}]},{"name":"Malanje Province","code":"MAL","cities":[{"name":"Malanje"}]},{"name":"Moxico Province","code":"MOX","cities":[{"name":"Léua"},{"name":"Luau"},{"name":"Luena"},{"name":"Lumeje"}]},{"name":"Uíge Province","code":"UIG","cities":[{"name":"Uíge"}]},{"name":"Zaire Province","code":"ZAI","cities":[{"name":"Mbanza Congo"},{"name":"N'zeto"},{"name":"Soio"}]}]}